breathpy/__init__.py
breathpy/generate_sample_data.py
breathpy/test.py
breathpy/bin/peax1.0-LinuxX64/LICENSE.txt
breathpy/bin/peax1.0-LinuxX64/README.txt
breathpy/bin/peax1.0-LinuxX64/parameters.cfg
breathpy/bin/peax1.0-LinuxX64/peax
breathpy/bin/peax1.0-LinuxX64/run_peax_list.py
breathpy/bin/peax1.0-LinuxX64/yoshiko
breathpy/model/BreathCore.py
breathpy/model/CoreTest.py
breathpy/model/GCMSTest.py
breathpy/model/GCMSTools.py
breathpy/model/ProcessingMethods.py
breathpy/model/Tests.py
breathpy/model/__init__.py
breathpy/tools/__init__.py
breathpy/tools/tools.py
breathpy/view/BreathVisualizations.py
breathpy/view/__init__.py
breathpy/view/venn.py
breathpy-0.9.6.dist-info/LICENSE
breathpy-0.9.6.dist-info/METADATA
breathpy-0.9.6.dist-info/WHEEL
breathpy-0.9.6.dist-info/top_level.txt
breathpy-0.9.6.dist-info/RECORD
