Metadata-Version: 2.1
Name: breathpy
Version: 0.9.6
Summary: Breath analysis in python
Home-page: https://github.com/philmaweb/breathpy
Author: Philipp Weber
Author-email: philmaweb@gmail.com
License: GPLv3
Platform: UNKNOWN
Classifier: Programming Language :: Python :: 3
Classifier: Programming Language :: Python :: 3.6
Classifier: License :: OSI Approved :: GNU General Public License v3 (GPLv3)
Requires-Python: >=3.6
Requires-Dist: graphviz (>=0.13.2)
Requires-Dist: ipdb
Requires-Dist: matplotlib (>=3.2.1)
Requires-Dist: matplotlib-venn (>=0.11.5)
Requires-Dist: numpy (>=1.18.1)
Requires-Dist: pandas (>=1.0.3)
Requires-Dist: psutil (>=3.4.2)
Requires-Dist: pyopenms (==2.5.0)
Requires-Dist: pywavelets (>=1.1.1)
Requires-Dist: scikit-image (>=0.16.2)
Requires-Dist: scikit-learn (<0.24.0,>=0.22.0)
Requires-Dist: scipy (>=1.4.1)
Requires-Dist: seaborn (>=0.10.0)
Requires-Dist: statannot (>=0.2.3)
Requires-Dist: statsmodels (>=0.11.1)
Requires-Dist: xlrd (>=1.2.0)
